trace_dkey/__init__.py
trace_dkey/__main__.py
trace_dkey/cmd.py
trace_dkey-0.0.8.dist-info/LICENSE
trace_dkey-0.0.8.dist-info/METADATA
trace_dkey-0.0.8.dist-info/WHEEL
trace_dkey-0.0.8.dist-info/entry_points.txt
trace_dkey-0.0.8.dist-info/top_level.txt
trace_dkey-0.0.8.dist-info/RECORD
