Metadata-Version: 2.1
Name: trace-dkey
Version: 0.0.8
Summary: Python library to trace path of a particular key inside a nested dict
Home-page: https://github.com/Agent-Hellboy/trace-dkey
Author: Prince Roshan
Author-email: princekrroshan01@gmail.com
License: MIT
Keywords: tracer,dict-key-path-finder
Classifier: Programming Language :: Python :: 3.9
Classifier: Programming Language :: Python :: 3.10
Classifier: Programming Language :: Python :: 3.11
Classifier: Programming Language :: Python :: 3.12
Classifier: Programming Language :: Python :: 3.13
Classifier: Operating System :: OS Independent
Requires-Python: >=3.9
License-File: LICENSE
Requires-Dist: click
